LICENSE
MANIFEST.in
README.rst
setup.py
modules/__init__.py
modules/module_serial/__init__.py
openedoo/__init__.py
openedoo/config.py
openedoo.egg-info/PKG-INFO
openedoo.egg-info/SOURCES.txt
openedoo.egg-info/dependency_links.txt
openedoo.egg-info/entry_points.txt
openedoo.egg-info/not-zip-safe
openedoo.egg-info/requires.txt
openedoo.egg-info/top_level.txt
openedoo/bin/openedoo-cli.py
openedoo/core/__init__.py
openedoo/core/db/__init__.py
openedoo/core/libs/__init__.py
openedoo/core/libs/get_modul.py
openedoo/core/libs/get_requirement.py
openedoo/core/libs/install_pip.py
openedoo/core/libs/token.py
openedoo/core/libs/tools.py
openedoo/core/management/__init__.py
openedoo/core/management/commands/__init__.py
openedoo/core/management/commands/create_module.py
openedoo/core/management/commands/create_module_app.py
openedoo/core/management/commands/create_project.py
openedoo/core/management/commands/delete_module.py
openedoo/core/management/commands/gunicornserver.py
openedoo/core/management/commands/install_module.py
openedoo/core/management/commands/install_openedoo.py
openedoo/core/management/commands/module.py
openedoo/core/management/commands/update_module.py
openedoo/core/management/commands/waiting_animated.py
openedoo/management/__init__.py
openedoo/management/commands/__init__.py
openedoo/management/commands/create_module.py
openedoo/management/commands/create_module_app.py
openedoo/management/commands/create_project.py
openedoo/management/commands/delete_module.py
openedoo/management/commands/gunicornserver.py
openedoo/management/commands/install_module.py
openedoo/management/commands/install_openedoo.py
openedoo/management/commands/module.py
openedoo/management/commands/testing_openedoo.py
openedoo/management/commands/update_module.py
openedoo/management/commands/version.py
openedoo/management/commands/waiting_animated.py
openedoo/template_conf/module_template/.gitignore
openedoo/template_conf/module_template/__init__.py
openedoo/template_conf/module_template/database.py
openedoo/template_conf/module_template/requirement.json
openedoo/template_conf/project_template/config.json
openedoo/template_conf/project_template/manage.py
